RagPUREAI_libs/RagPUREAI_libs.cpython-312-x86_64-linux-gnu.so
RagPUREAI_libs/__init__.py
RagPUREAI_libs-0.1.3.dist-info/METADATA
RagPUREAI_libs-0.1.3.dist-info/WHEEL
RagPUREAI_libs-0.1.3.dist-info/top_level.txt
RagPUREAI_libs-0.1.3.dist-info/RECORD
