Metadata-Version: 2.2
Name: RagPUREAI_libs
Version: 0.1.3
Summary: Binding de C++ e Python
Author: Seu Nome
Author-email: seu.email@exemplo.com
Classifier: Programming Language :: Python :: 3
Classifier: Operating System :: POSIX :: Linux
Dynamic: author
Dynamic: author-email
Dynamic: classifier
Dynamic: summary
